{"name":"Ta Là Nữ Nhưng Lại Xuyên Thành Hoàng Tử Phản Diện","folder":"talanunhunglaixuyenthanhhoangtuphandien","tacGia":"KĐT Diệu Kỳ","theLoai":"Bách Hợp","trangThai":"Full","description":"Tác phẩm: Ta Là Nữ, Nhưng Lại Xuyên Thành Hoàng Tử Phản Diện<br><br>Thể loại: Xuyên Không, Bách Hợp, Cổ Đại.<br><br>Triệu Minh Ngọc sẽ tốt nghiệp trong năm nay và trở thành giáo viên Toán. Cuộc sống của cô ấy yên bình, đơn giản cho đến khi một hoa khôi đẹp trai cô đi bơi và làm cô hạnh phúc vô cùng. Minh Ngọc tin rằng hoa khôi này cũng đã phải lòng mình từ lâu.<br><br>Tuy nhiên, trên đường đi gặp gỡ, Minh Ngọc bị tai nạn giao thông và qua đời một cách tiếc nuối.<br><br>Cô đã nghĩ rằng mình đã chết, nhưng bất ngờ bị đưa đến một thế giới khác - thế giới của cuốn tiểu thuyết mình từng sáng tác. Nếu chưa đủ xui xẻo, cô ấy còn xuyên thành nam hoàng tử phản diện trong truyện. Chỉ có điều rằng lập trường của hoàng tử này là giết chết cặp đôi chính.<br><br>Minh Ngọc phải làm gì để tồn tại trong thế giới mới này? Làm sao để tránh khỏi việc bị giết bởi cặp đôi chính đầy tình yêu?<br><br>Nếu bạn yêu thích truyện bách hợp, hãy đọc thêm Bị Bắt Trở Thành Nữ Vai Ác Tiểu Kiều Thê hoặc Sau Khi Dưỡng Thành Đại Nông Hộ.&nbsp;"}