{"name":"Kẻ Khùng Người Điên","folder":"kekhungnguoidjien","tacGia":"Jin Ruan","theLoai":"Ngôn Tình","trangThai":"Đang ra","description":"Châu Thanh là cảnh sát hình sự, trong một lần theo dõi tội phạm, cô bị tên cầm đầu phát hiện. Sau khi hành hung, chúng nhốt cô vào căn nhà hoang gần bìa rừng biên giới và phóng hỏa.<br><br>May mắn được ông chú lạ mặt Lục Hoài Nam cứu nhưng chấn thương ảnh hưởng lớn đến não bộ, đầu óc của Châu Thanh bây giờ chỉ còn lại nhận thức của đứa trẻ 7 tuổi.<br><br>Lục Hoài Nam vô tình nhặt được \"của nợ\" Châu Thanh, trùng hợp mẹ anh cũng đang cần một cô con dâu. Cô gái này vừa hay có thể lợi dụng.<br><br>Tác giả: Jin Ruan"}