{"name":"Sau Khi Dưỡng Thành Đại Nông Hộ","folder":"saukhiduongthanhdjainongho","tacGia":"Phương Tiện Diện Quân","theLoai":"Huyền Huyễn","trangThai":"Đang ra","description":"Tác giả: Phương Tiện Diện Quân<br><br>Thể loại: Xuyên Không, Cổ Đại, Bách Hợp, Điền Văn, Huyền Huyễn<br><br>Giới thiệu:<br><br>Chu Thư là một thương nhân kinh doanh trà nổi tiếng ở Tín Châu.<br><br>Hôm ấy nàng đến vườn trà xem xét, quản sự vội vàng nói với nàng rằng heo bên nông trường cạnh đã ủn hết vườn trà rồi.<br><br>Chủ nhân nông trường là công tử của Kỳ gia, tên Kỳ Hữu Vọng cùng với hạ nhân vội vàng chạy tới muốn bắt heo.<br><br>Không ngờ vừa gặp Chu Thư, công tử đã nhằm vào nàng, nói rằng muốn \"ủn\" nàng. Sau này - -<br><br>Có người hỏi Kỳ Hữu Vọng, vì sao thịt heo nàng nuôi lại ăn ngon đến vậy.<br><br>Kỳ Hữu Vọng nhìn giấy tờ nương tử nhà mình đưa qua, phát sầu: Đương nhiên là ngon rồi, đều là ăn (tiền) lá trà mà lớn lên đó!"}