{"name":"[Địa Sư Kiều Mặc Vũ] - Lạc Trong Núi Ai Lao","folder":"djiasukieumacvulactrongnuiailao","tacGia":"Zhihu/Sữa Chua Vị Xoài","theLoai":"Đô Thị","trangThai":"Full","description":"[ĐỊA SƯ KIỀU MẶC VŨ] - LẠC TRONG NÚI AI LAO<br><br>Tác giả: Sữa Chua Vị Xoài<br><br>Thể loại: hiện đại, tâm linh, linh dị, hài hước, xem phong thuỷ bắt ma.<br><br>Giới thiệu:<br><br>Gần đây giới giải trí nổi lên một làn sóng huyền học, vì vậy một chương trình giải trí thám hiểm đã được tổ chức. Tổ tiết mục mời hai đại sư phong thủy đến trấn giữ, một người là đại sư ở Hong Kong, một người là tôi.<br><br>Tất cả mọi người đều cười nhạo tôi trẻ tuổi, bọn họ không biết, tôi là truyền nhân duy nhất của Địa sư."}